{
  "symbol": "B3109A",
  "fetchedAt": "2026-02-24T20:18:11Z",
  "source": "BVB",
  "details": {
    "faceValue": 5000.0,
    "currency": "RON",
    "couponRate": 3.65,
    "interestType": "fixed",
    "issueDate": "2016-10-10",
    "maturityDate": "2031-09-24",
    "couponFrequency": 1
  },
  "annualRate": 3.65,
  "frequency": 1,
  "couponCount": 15,
  "payments": [
    {
      "paymentDate": "2016-09-24",
      "previousDate": "2015-09-24",
      "referenceDate": "2016-09-22",
      "couponRate": 3.65,
      "number": 1
    },
    {
      "paymentDate": "2018-09-24",
      "previousDate": "2017-09-24",
      "referenceDate": "2018-09-21",
      "couponRate": 3.65,
      "number": 2
    },
    {
      "paymentDate": "2019-09-24",
      "previousDate": "2018-09-24",
      "referenceDate": "2019-09-23",
      "couponRate": 3.65,
      "number": 3
    },
    {
      "paymentDate": "2020-09-24",
      "previousDate": "2019-09-24",
      "referenceDate": "2020-09-23",
      "couponRate": 3.65,
      "number": 4
    },
    {
      "paymentDate": "2021-09-24",
      "previousDate": "2020-09-24",
      "referenceDate": "2021-09-23",
      "couponRate": 3.65,
      "number": 5
    },
    {
      "paymentDate": "2022-09-24",
      "previousDate": "2021-09-24",
      "referenceDate": "2022-09-23",
      "couponRate": 3.65,
      "number": 6
    },
    {
      "paymentDate": "2023-09-24",
      "previousDate": "2022-09-24",
      "referenceDate": "2023-09-22",
      "couponRate": 3.65,
      "number": 7
    },
    {
      "paymentDate": "2024-09-24",
      "previousDate": "2023-09-24",
      "referenceDate": "2024-09-23",
      "couponRate": 3.65,
      "number": 8
    },
    {
      "paymentDate": "2025-09-24",
      "previousDate": "2024-09-24",
      "referenceDate": "2025-09-23",
      "couponRate": 3.65,
      "number": 9
    },
    {
      "paymentDate": "2026-09-24",
      "previousDate": "2025-09-24",
      "referenceDate": "2026-09-23",
      "couponRate": 3.65,
      "number": 10
    },
    {
      "paymentDate": "2027-09-24",
      "previousDate": "2026-09-24",
      "referenceDate": "2027-09-23",
      "couponRate": 3.65,
      "number": 11
    },
    {
      "paymentDate": "2028-09-24",
      "previousDate": "2027-09-24",
      "referenceDate": "2028-09-22",
      "couponRate": 3.65,
      "number": 12
    },
    {
      "paymentDate": "2029-09-24",
      "previousDate": "2028-09-24",
      "referenceDate": "2029-09-21",
      "couponRate": 3.65,
      "number": 13
    },
    {
      "paymentDate": "2030-09-24",
      "previousDate": "2029-09-24",
      "referenceDate": "2030-09-23",
      "couponRate": 3.65,
      "number": 14
    },
    {
      "paymentDate": "2031-09-24",
      "previousDate": "2030-09-24",
      "referenceDate": "2031-09-23",
      "couponRate": 3.65,
      "number": 15
    }
  ],
  "principalRepayments": [
    {
      "date": "2031-09-23",
      "number": 1,
      "principal": 5000.0,
      "repaymentAmount": 5000.0
    }
  ]
}