{
  "symbol": "R2710B",
  "fetchedAt": "2026-02-24T20:26:38Z",
  "source": "BVB",
  "details": {
    "faceValue": 100.0,
    "currency": "RON",
    "couponRate": 8.2,
    "interestType": "fixed",
    "issueDate": "2025-10-22",
    "maturityDate": "2027-10-22",
    "couponFrequency": 1
  },
  "annualRate": 8.2,
  "frequency": 1,
  "couponCount": 2,
  "payments": [
    {
      "paymentDate": "2026-10-22",
      "previousDate": "2025-10-22",
      "referenceDate": "2026-10-13",
      "couponRate": 8.2,
      "number": 1
    },
    {
      "paymentDate": "2027-10-22",
      "previousDate": "2026-10-22",
      "referenceDate": "2027-10-13",
      "couponRate": 8.2,
      "number": 2
    }
  ],
  "principalRepayments": [
    {
      "date": "2027-10-13",
      "number": 1,
      "principal": 100.0,
      "repaymentAmount": 100.0
    }
  ]
}