{
  "symbol": "R3108A",
  "fetchedAt": "2026-02-24T20:31:25Z",
  "source": "BVB",
  "details": {
    "faceValue": 100.0,
    "currency": "RON",
    "couponRate": 7.9,
    "interestType": "fixed",
    "issueDate": "2025-08-13",
    "maturityDate": "2031-08-13",
    "couponFrequency": 1
  },
  "annualRate": 7.9,
  "frequency": 1,
  "couponCount": 6,
  "payments": [
    {
      "paymentDate": "2026-08-13",
      "previousDate": "2025-08-13",
      "referenceDate": "2026-08-04",
      "couponRate": 7.9,
      "number": 1
    },
    {
      "paymentDate": "2027-08-13",
      "previousDate": "2026-08-13",
      "referenceDate": "2027-08-04",
      "couponRate": 7.9,
      "number": 2
    },
    {
      "paymentDate": "2028-08-13",
      "previousDate": "2027-08-13",
      "referenceDate": "2028-08-03",
      "couponRate": 7.9,
      "number": 3
    },
    {
      "paymentDate": "2029-08-13",
      "previousDate": "2028-08-13",
      "referenceDate": "2029-08-02",
      "couponRate": 7.9,
      "number": 4
    },
    {
      "paymentDate": "2030-08-13",
      "previousDate": "2029-08-13",
      "referenceDate": "2030-08-02",
      "couponRate": 7.9,
      "number": 5
    },
    {
      "paymentDate": "2031-08-13",
      "previousDate": "2030-08-13",
      "referenceDate": "2031-08-04",
      "couponRate": 7.9,
      "number": 6
    }
  ],
  "principalRepayments": [
    {
      "date": "2031-08-04",
      "number": 1,
      "principal": 100.0,
      "repaymentAmount": 100.0
    }
  ]
}