{
  "date": "2026-02-19",
  "fetchedAt": "2026-02-19T17:43:58Z",
  "source": "BVB",
  "bondCount": 116,
  "bonds": [
    {
      "symbol": "AAB26",
      "name": "AGROLAND AGRIBUSINESS - 2026",
      "market": "XRB",
      "trades": 4,
      "volume": 53.0,
      "value": 5324.64,
      "open": 99.99,
      "low": 99.94,
      "high": 99.99,
      "avg": 99.95,
      "close": 99.95,
      "refPrice": 100.0,
      "changePercent": -0.05
    },
    {
      "symbol": "AGR28",
      "name": "Agroland Business System Bonds 2028",
      "market": "XRB",
      "trades": 2,
      "volume": 35.0,
      "value": 3613.28,
      "open": 99.87,
      "low": 99.31,
      "high": 99.87,
      "avg": 99.39,
      "close": 99.31,
      "refPrice": 99.87,
      "changePercent": -0.56
    },
    {
      "symbol": "ANS26E",
      "name": "Ansett Logistics Obligatiuni Euro 2026",
      "market": "EXRB",
      "trades": 1,
      "volume": 5.0,
      "value": 2535.18,
      "open": 99.0,
      "low": 99.0,
      "high": 99.0,
      "avg": 99.0,
      "close": 99.0,
      "refPrice": 99.0,
      "changePercent": 0.0
    },
    {
      "symbol": "ATPR28",
      "name": "ARTPRINT - 2028",
      "market": "XRB",
      "trades": 2,
      "volume": 10.0,
      "value": 962.72,
      "open": 94.0,
      "low": 94.0,
      "high": 94.0,
      "avg": 94.0,
      "close": 94.0,
      "refPrice": 94.53,
      "changePercent": -0.56
    },
    {
      "symbol": "JOBS26E",
      "name": "BESTJOBS RECRUTARE - Obligatiuni 2026 EUR",
      "market": "EXRB",
      "trades": 5,
      "volume": 21.0,
      "value": 51990.49,
      "open": 95.5,
      "low": 95.5,
      "high": 96.0,
      "avg": 95.69,
      "close": 96.0,
      "refPrice": 95.99,
      "changePercent": 0.01
    },
    {
      "symbol": "BNET28",
      "name": "BITTNET SYSTEMS",
      "market": "ORDB",
      "trades": 3,
      "volume": 40.0,
      "value": 3910.03,
      "open": 96.0,
      "low": 95.91,
      "high": 96.0,
      "avg": 95.94,
      "close": 95.92,
      "refPrice": 96.4,
      "changePercent": -0.5
    },
    {
      "symbol": "BNET26E",
      "name": "BITTNET SYSTEMS - 2026E",
      "market": "EORDB",
      "trades": 7,
      "volume": 49.0,
      "value": 25467.91,
      "open": 100.6,
      "low": 100.6,
      "high": 100.85,
      "avg": 100.7,
      "close": 100.85,
      "refPrice": 100.6,
      "changePercent": 0.25
    },
    {
      "symbol": "BNET28A",
      "name": "BITTNET SYSTEMS Bonds 2028A",
      "market": "ORDB",
      "trades": 8,
      "volume": 657.0,
      "value": 63614.17,
      "open": 95.68,
      "low": 95.68,
      "high": 96.0,
      "avg": 95.95,
      "close": 96.0,
      "refPrice": 95.5,
      "changePercent": 0.52
    },
    {
      "symbol": "BNET27A",
      "name": "BITTNET SYSTEMS- Ob. 2027",
      "market": "ORDB",
      "trades": 3,
      "volume": 94.0,
      "value": 9521.5,
      "open": 99.6,
      "low": 99.6,
      "high": 99.72,
      "avg": 99.71,
      "close": 99.72,
      "refPrice": 98.62,
      "changePercent": 1.12
    },
    {
      "symbol": "ELF26",
      "name": "ELEFANT ONLINE",
      "market": "XRB",
      "trades": 3,
      "volume": 238.0,
      "value": 1116.8,
      "open": 2.49,
      "low": 2.49,
      "high": 2.5,
      "avg": 2.5,
      "close": 2.5,
      "refPrice": 2.18,
      "changePercent": 14.68
    },
    {
      "symbol": "IMPI27E",
      "name": "IMPETUM - 2027",
      "market": "EXRB",
      "trades": 1,
      "volume": 2.0,
      "value": 10425.74,
      "open": 101.0,
      "low": 101.0,
      "high": 101.0,
      "avg": 101.0,
      "close": 101.0,
      "refPrice": 100.99,
      "changePercent": 0.01
    },
    {
      "symbol": "R2603A",
      "name": "MINISTERUL FINANTELOR",
      "market": "REGT",
      "trades": 20,
      "volume": 2509.0,
      "value": 266845.94,
      "open": 100.0699,
      "low": 99.93,
      "high": 100.07,
      "avg": 100.0055,
      "close": 100.07,
      "refPrice": 99.9101,
      "changePercent": 0.16
    },
    {
      "symbol": "R2603B",
      "name": "MINISTERUL FINANTELOR",
      "market": "REGT",
      "trades": 2,
      "volume": 310.0,
      "value": 33324.9,
      "open": 100.2,
      "low": 100.2,
      "high": 100.21,
      "avg": 100.2097,
      "close": 100.21,
      "refPrice": 100.1,
      "changePercent": 0.11
    },
    {
      "symbol": "R2604A",
      "name": "MINISTERUL FINANTELOR",
      "market": "REGT",
      "trades": 1,
      "volume": 4.0,
      "value": 425.44,
      "open": 100.0001,
      "low": 100.0001,
      "high": 100.0001,
      "avg": 100.0001,
      "close": 100.0001,
      "refPrice": 100.439,
      "changePercent": -0.44
    },
    {
      "symbol": "R2604B",
      "name": "MINISTERUL FINANTELOR",
      "market": "REGT",
      "trades": 6,
      "volume": 472.0,
      "value": 50474.45,
      "open": 100.4,
      "low": 100.4,
      "high": 100.425,
      "avg": 100.421,
      "close": 100.41,
      "refPrice": 100.4249,
      "changePercent": -0.01
    },
    {
      "symbol": "R2604C",
      "name": "MINISTERUL FINANTELOR",
      "market": "REGT",
      "trades": 15,
      "volume": 1452.0,
      "value": 153704.0,
      "open": 100.0,
      "low": 100.0,
      "high": 100.33,
      "avg": 100.1984,
      "close": 100.33,
      "refPrice": 99.86,
      "changePercent": 0.47
    },
    {
      "symbol": "R2605A",
      "name": "MINISTERUL FINANTELOR",
      "market": "REGT",
      "trades": 8,
      "volume": 454.0,
      "value": 47907.0,
      "open": 100.4199,
      "low": 100.2,
      "high": 100.44,
      "avg": 100.382,
      "close": 100.44,
      "refPrice": 100.4199,
      "changePercent": 0.02
    },
    {
      "symbol": "R2605B",
      "name": "MINISTERUL FINANTELOR",
      "market": "REGT",
      "trades": 9,
      "volume": 1445.0,
      "value": 153947.25,
      "open": 100.45,
      "low": 100.45,
      "high": 101.45,
      "avg": 100.6379,
      "close": 101.3501,
      "refPrice": 100.45,
      "changePercent": 0.9
    },
    {
      "symbol": "R2608A",
      "name": "MINISTERUL FINANTELOR",
      "market": "REGT",
      "trades": 36,
      "volume": 2711.0,
      "value": 283228.11,
      "open": 100.3,
      "low": 100.3,
      "high": 100.55,
      "avg": 100.4333,
      "close": 100.455,
      "refPrice": 100.26,
      "changePercent": 0.19
    },
    {
      "symbol": "R2610A",
      "name": "MINISTERUL FINANTELOR",
      "market": "REGT",
      "trades": 28,
      "volume": 4362.0,
      "value": 449688.9,
      "open": 100.35,
      "low": 100.1102,
      "high": 100.6969,
      "avg": 100.3723,
      "close": 100.6969,
      "refPrice": 100.2,
      "changePercent": 0.5
    },
    {
      "symbol": "R2610AE",
      "name": "MINISTERUL FINANTELOR",
      "market": "EREGT",
      "trades": 7,
      "volume": 280.0,
      "value": 142609.0,
      "open": 99.449,
      "low": 98.8002,
      "high": 99.455,
      "avg": 99.3704,
      "close": 98.8002,
      "refPrice": 99.445,
      "changePercent": -0.65
    },
    {
      "symbol": "R2612A",
      "name": "MINISTERUL FINANTELOR",
      "market": "REGT",
      "trades": 18,
      "volume": 1450.0,
      "value": 148056.32,
      "open": 100.7399,
      "low": 100.7399,
      "high": 100.88,
      "avg": 100.8175,
      "close": 100.85,
      "refPrice": 100.4,
      "changePercent": 0.45
    },
    {
      "symbol": "R2612BE",
      "name": "MINISTERUL FINANTELOR",
      "market": "EREGT",
      "trades": 3,
      "volume": 43.0,
      "value": 22180.0,
      "open": 100.35,
      "low": 100.35,
      "high": 100.85,
      "avg": 100.6174,
      "close": 100.85,
      "refPrice": 100.35,
      "changePercent": 0.5
    },
    {
      "symbol": "R2702AE",
      "name": "MINISTERUL FINANTELOR",
      "market": "EREGT",
      "trades": 12,
      "volume": 381.0,
      "value": 196056.71,
      "open": 100.9,
      "low": 100.9,
      "high": 100.99,
      "avg": 100.9751,
      "close": 100.98,
      "refPrice": 100.9,
      "changePercent": 0.08
    },
    {
      "symbol": "R2703A",
      "name": "MINISTERUL FINANTELOR",
      "market": "REGT",
      "trades": 41,
      "volume": 7027.0,
      "value": 750066.13,
      "open": 100.0,
      "low": 100.0,
      "high": 100.3,
      "avg": 100.1916,
      "close": 100.25,
      "refPrice": 100.0,
      "changePercent": 0.25
    },
    {
      "symbol": "R2703AE",
      "name": "MINISTERUL FINANTELOR",
      "market": "EREGT",
      "trades": 1,
      "volume": 1.0,
      "value": 529.79,
      "open": 100.5,
      "low": 100.5,
      "high": 100.5,
      "avg": 100.5,
      "close": 100.5,
      "refPrice": 100.1,
      "changePercent": 0.4
    },
    {
      "symbol": "R2704A",
      "name": "MINISTERUL FINANTELOR",
      "market": "REGT",
      "trades": 27,
      "volume": 3622.0,
      "value": 383796.76,
      "open": 100.0,
      "low": 100.0,
      "high": 100.4,
      "avg": 100.202,
      "close": 100.15,
      "refPrice": 100.0,
      "changePercent": 0.15
    },
    {
      "symbol": "R2704AE",
      "name": "MINISTERUL FINANTELOR",
      "market": "EREGT",
      "trades": 5,
      "volume": 41.0,
      "value": 21630.7,
      "open": 100.4699,
      "low": 100.4699,
      "high": 100.4799,
      "avg": 100.4761,
      "close": 100.4799,
      "refPrice": 99.8,
      "changePercent": 0.68
    },
    {
      "symbol": "R2705AE",
      "name": "MINISTERUL FINANTELOR",
      "market": "EREGT",
      "trades": 1,
      "volume": 130.0,
      "value": 67931.5,
      "open": 99.65,
      "low": 99.65,
      "high": 99.65,
      "avg": 99.65,
      "close": 99.65,
      "refPrice": 99.45,
      "changePercent": 0.2
    },
    {
      "symbol": "R2706A",
      "name": "MINISTERUL FINANTELOR",
      "market": "REGT",
      "trades": 11,
      "volume": 609.0,
      "value": 64441.69,
      "open": 100.55,
      "low": 100.55,
      "high": 100.98,
      "avg": 100.8049,
      "close": 100.5601,
      "refPrice": 100.2,
      "changePercent": 0.36
    },
    {
      "symbol": "R2706B",
      "name": "MINISTERUL FINANTELOR",
      "market": "REGT",
      "trades": 17,
      "volume": 560.0,
      "value": 60332.18,
      "open": 102.0,
      "low": 101.998,
      "high": 102.144,
      "avg": 102.0366,
      "close": 102.144,
      "refPrice": 102.0,
      "changePercent": 0.14
    },
    {
      "symbol": "R2707A",
      "name": "MINISTERUL FINANTELOR",
      "market": "REGT",
      "trades": 6,
      "volume": 150.0,
      "value": 15652.6,
      "open": 99.7002,
      "low": 99.7002,
      "high": 100.1284,
      "avg": 99.9405,
      "close": 100.0503,
      "refPrice": 99.7,
      "changePercent": 0.35
    },
    {
      "symbol": "R2707AE",
      "name": "MINISTERUL FINANTELOR",
      "market": "EREGT",
      "trades": 3,
      "volume": 100.0,
      "value": 51805.79,
      "open": 99.5799,
      "low": 99.5799,
      "high": 99.7,
      "avg": 99.6268,
      "close": 99.7,
      "refPrice": 99.05,
      "changePercent": 0.66
    },
    {
      "symbol": "R2707B",
      "name": "MINISTERUL FINANTELOR",
      "market": "REGT",
      "trades": 2,
      "volume": 58.0,
      "value": 6199.86,
      "open": 101.9,
      "low": 101.7501,
      "high": 101.9,
      "avg": 101.8742,
      "close": 101.7501,
      "refPrice": 101.4001,
      "changePercent": 0.35
    },
    {
      "symbol": "R2707C",
      "name": "MINISTERUL FINANTELOR",
      "market": "REGT",
      "trades": 26,
      "volume": 8709.0,
      "value": 913201.19,
      "open": 100.142,
      "low": 100.1235,
      "high": 100.8399,
      "avg": 100.4472,
      "close": 100.6,
      "refPrice": 100.19,
      "changePercent": 0.41
    },
    {
      "symbol": "R2708A",
      "name": "MINISTERUL FINANTELOR",
      "market": "REGT",
      "trades": 16,
      "volume": 1954.0,
      "value": 203523.72,
      "open": 100.3,
      "low": 100.15,
      "high": 100.7,
      "avg": 100.3275,
      "close": 100.2605,
      "refPrice": 100.2,
      "changePercent": 0.06
    },
    {
      "symbol": "R2708B",
      "name": "MINISTERUL FINANTELOR",
      "market": "REGT",
      "trades": 4,
      "volume": 73.0,
      "value": 7756.73,
      "open": 101.85,
      "low": 101.85,
      "high": 101.9,
      "avg": 101.8961,
      "close": 101.9,
      "refPrice": 101.85,
      "changePercent": 0.05
    },
    {
      "symbol": "R2709A",
      "name": "MINISTERUL FINANTELOR",
      "market": "REGT",
      "trades": 18,
      "volume": 2715.0,
      "value": 281218.95,
      "open": 100.4398,
      "low": 100.4,
      "high": 100.4895,
      "avg": 100.4397,
      "close": 100.4895,
      "refPrice": 100.0,
      "changePercent": 0.49
    },
    {
      "symbol": "R2709AE",
      "name": "MINISTERUL FINANTELOR",
      "market": "EREGT",
      "trades": 5,
      "volume": 242.0,
      "value": 123717.73,
      "open": 99.01,
      "low": 99.0,
      "high": 99.01,
      "avg": 99.0081,
      "close": 99.0,
      "refPrice": 99.01,
      "changePercent": -0.01
    },
    {
      "symbol": "R2709B",
      "name": "MINISTERUL FINANTELOR",
      "market": "REGT",
      "trades": 7,
      "volume": 380.0,
      "value": 40100.61,
      "open": 101.8395,
      "low": 101.8395,
      "high": 102.0,
      "avg": 101.9579,
      "close": 102.0,
      "refPrice": 101.7,
      "changePercent": 0.29
    },
    {
      "symbol": "R2710A",
      "name": "MINISTERUL FINANTELOR",
      "market": "REGT",
      "trades": 11,
      "volume": 971.0,
      "value": 99902.82,
      "open": 100.37,
      "low": 100.37,
      "high": 100.4968,
      "avg": 100.4372,
      "close": 100.48,
      "refPrice": 100.45,
      "changePercent": 0.03
    },
    {
      "symbol": "R2710B",
      "name": "MINISTERUL FINANTELOR",
      "market": "REGT",
      "trades": 10,
      "volume": 1088.0,
      "value": 113989.94,
      "open": 102.0897,
      "low": 101.77,
      "high": 102.0898,
      "avg": 101.9802,
      "close": 101.77,
      "refPrice": 102.0993,
      "changePercent": -0.32
    },
    {
      "symbol": "R2711A",
      "name": "MINISTERUL FINANTELOR",
      "market": "REGT",
      "trades": 13,
      "volume": 1091.0,
      "value": 111059.44,
      "open": 99.9699,
      "low": 99.9001,
      "high": 100.2499,
      "avg": 99.966,
      "close": 100.0,
      "refPrice": 99.73,
      "changePercent": 0.27
    },
    {
      "symbol": "R2711B",
      "name": "MINISTERUL FINANTELOR",
      "market": "REGT",
      "trades": 9,
      "volume": 916.0,
      "value": 95234.74,
      "open": 101.81,
      "low": 101.5,
      "high": 101.8997,
      "avg": 101.8778,
      "close": 101.5,
      "refPrice": 101.899,
      "changePercent": -0.39
    },
    {
      "symbol": "R2712A",
      "name": "MINISTERUL FINANTELOR",
      "market": "REGT",
      "trades": 2,
      "volume": 105.0,
      "value": 10624.15,
      "open": 99.9897,
      "low": 99.7,
      "high": 99.9897,
      "avg": 99.9621,
      "close": 99.7,
      "refPrice": 99.61,
      "changePercent": 0.09
    },
    {
      "symbol": "R2712B",
      "name": "MINISTERUL FINANTELOR",
      "market": "REGT",
      "trades": 6,
      "volume": 670.0,
      "value": 68977.95,
      "open": 101.8999,
      "low": 101.2501,
      "high": 101.8999,
      "avg": 101.6121,
      "close": 101.4501,
      "refPrice": 101.5,
      "changePercent": -0.05
    },
    {
      "symbol": "R2712D",
      "name": "MINISTERUL FINANTELOR",
      "market": "REGT",
      "trades": 7,
      "volume": 622.0,
      "value": 63814.58,
      "open": 101.18,
      "low": 101.0,
      "high": 101.2,
      "avg": 101.1858,
      "close": 101.0,
      "refPrice": 101.18,
      "changePercent": -0.18
    },
    {
      "symbol": "R2801A",
      "name": "MINISTERUL FINANTELOR",
      "market": "REGT",
      "trades": 5,
      "volume": 122.0,
      "value": 12326.72,
      "open": 99.8001,
      "low": 99.8001,
      "high": 100.75,
      "avg": 100.5787,
      "close": 99.8001,
      "refPrice": 100.7499,
      "changePercent": -0.94
    },
    {
      "symbol": "R2801B",
      "name": "MINISTERUL FINANTELOR",
      "market": "REGT",
      "trades": 11,
      "volume": 483.0,
      "value": 49032.27,
      "open": 100.944,
      "low": 100.944,
      "high": 101.099,
      "avg": 100.9852,
      "close": 100.944,
      "refPrice": 100.85,
      "changePercent": 0.09
    },
    {
      "symbol": "R2802A",
      "name": "MINISTERUL FINANTELOR",
      "market": "REGT",
      "trades": 29,
      "volume": 3472.0,
      "value": 352418.32,
      "open": 101.0,
      "low": 101.0,
      "high": 101.99,
      "avg": 101.4224,
      "close": 101.2633,
      "refPrice": 101.0,
      "changePercent": 0.26
    },
    {
      "symbol": "R2802B",
      "name": "MINISTERUL FINANTELOR",
      "market": "REGT",
      "trades": 26,
      "volume": 4869.0,
      "value": 490298.1,
      "open": 100.6,
      "low": 100.51,
      "high": 100.64,
      "avg": 100.5984,
      "close": 100.585,
      "refPrice": 100.0,
      "changePercent": 0.59
    },
    {
      "symbol": "R2802C",
      "name": "MINISTERUL FINANTELOR",
      "market": "REGT",
      "trades": 3,
      "volume": 500.0,
      "value": 50090.0,
      "open": 100.1,
      "low": 100.1,
      "high": 100.1,
      "avg": 100.1,
      "close": 100.1,
      "refPrice": 100.0,
      "changePercent": 0.1
    },
    {
      "symbol": "R2803A",
      "name": "MINISTERUL FINANTELOR",
      "market": "REGT",
      "trades": 24,
      "volume": 3923.0,
      "value": 423649.92,
      "open": 101.3898,
      "low": 100.8699,
      "high": 101.49,
      "avg": 100.9813,
      "close": 100.872,
      "refPrice": 100.7,
      "changePercent": 0.17
    },
    {
      "symbol": "R2804A",
      "name": "MINISTERUL FINANTELOR",
      "market": "REGT",
      "trades": 12,
      "volume": 3638.0,
      "value": 382687.94,
      "open": 100.02,
      "low": 98.0,
      "high": 100.94,
      "avg": 98.9318,
      "close": 100.542,
      "refPrice": 100.9395,
      "changePercent": -0.39
    },
    {
      "symbol": "R2804AE",
      "name": "MINISTERUL FINANTELOR",
      "market": "EREGT",
      "trades": 13,
      "volume": 669.0,
      "value": 366925.73,
      "open": 102.6479,
      "low": 102.5,
      "high": 102.6849,
      "avg": 102.6475,
      "close": 102.6849,
      "refPrice": 102.51,
      "changePercent": 0.17
    },
    {
      "symbol": "R2805A",
      "name": "MINISTERUL FINANTELOR",
      "market": "REGT",
      "trades": 3,
      "volume": 11.0,
      "value": 1176.3,
      "open": 109.0,
      "low": 100.21,
      "high": 109.0,
      "avg": 101.2964,
      "close": 100.21,
      "refPrice": 109.0,
      "changePercent": -8.06
    },
    {
      "symbol": "R2808AE",
      "name": "MINISTERUL FINANTELOR",
      "market": "EREGT",
      "trades": 1,
      "volume": 21.0,
      "value": 11206.86,
      "open": 101.7021,
      "low": 101.7021,
      "high": 101.7021,
      "avg": 101.7021,
      "close": 101.7021,
      "refPrice": 102.5,
      "changePercent": -0.78
    },
    {
      "symbol": "R2810CE",
      "name": "MINISTERUL FINANTELOR",
      "market": "EREGT",
      "trades": 1,
      "volume": 25.0,
      "value": 12821.75,
      "open": 99.27,
      "low": 99.27,
      "high": 99.27,
      "avg": 99.27,
      "close": 99.27,
      "refPrice": 99.55,
      "changePercent": -0.28
    },
    {
      "symbol": "R2812AE",
      "name": "MINISTERUL FINANTELOR",
      "market": "EREGT",
      "trades": 8,
      "volume": 1131.0,
      "value": 593311.29,
      "open": 101.9984,
      "low": 101.9984,
      "high": 102.0001,
      "avg": 101.9999,
      "close": 102.0,
      "refPrice": 101.89,
      "changePercent": 0.11
    },
    {
      "symbol": "R2812CE",
      "name": "MINISTERUL FINANTELOR",
      "market": "EREGT",
      "trades": 1,
      "volume": 23.0,
      "value": 11810.27,
      "open": 100.1,
      "low": 100.1,
      "high": 100.1,
      "avg": 100.1,
      "close": 100.1,
      "refPrice": 99.1,
      "changePercent": 1.01
    },
    {
      "symbol": "R2904AE",
      "name": "MINISTERUL FINANTELOR",
      "market": "EREGT",
      "trades": 9,
      "volume": 897.0,
      "value": 478521.0,
      "open": 100.4999,
      "low": 100.4999,
      "high": 100.7,
      "avg": 100.5134,
      "close": 100.5,
      "refPrice": 100.0,
      "changePercent": 0.5
    },
    {
      "symbol": "R2906A",
      "name": "MINISTERUL FINANTELOR",
      "market": "REGT",
      "trades": 5,
      "volume": 140.0,
      "value": 14991.7,
      "open": 101.108,
      "low": 101.108,
      "high": 101.89,
      "avg": 101.8334,
      "close": 101.89,
      "refPrice": 101.88,
      "changePercent": 0.01
    },
    {
      "symbol": "R2907A",
      "name": "MINISTERUL FINANTELOR",
      "market": "REGT",
      "trades": 3,
      "volume": 30.0,
      "value": 3219.3,
      "open": 103.498,
      "low": 100.886,
      "high": 103.498,
      "avg": 102.6273,
      "close": 100.886,
      "refPrice": 103.0,
      "changePercent": -2.05
    },
    {
      "symbol": "R2907AE",
      "name": "MINISTERUL FINANTELOR",
      "market": "EREGT",
      "trades": 7,
      "volume": 4321.0,
      "value": 2272025.01,
      "open": 100.0,
      "low": 100.0,
      "high": 100.0,
      "avg": 100.0,
      "close": 100.0,
      "refPrice": 100.0,
      "changePercent": 0.0
    },
    {
      "symbol": "R2908A",
      "name": "MINISTERUL FINANTELOR",
      "market": "REGT",
      "trades": 19,
      "volume": 7317.0,
      "value": 756309.56,
      "open": 99.75,
      "low": 99.55,
      "high": 99.89,
      "avg": 99.8333,
      "close": 99.8,
      "refPrice": 99.75,
      "changePercent": 0.05
    },
    {
      "symbol": "R2908C",
      "name": "MINISTERUL FINANTELOR",
      "market": "REGT",
      "trades": 1,
      "volume": 10.0,
      "value": 1042.3,
      "open": 100.1601,
      "low": 100.1601,
      "high": 100.1601,
      "avg": 100.1601,
      "close": 100.1601,
      "refPrice": 102.93,
      "changePercent": -2.69
    },
    {
      "symbol": "R2909A",
      "name": "MINISTERUL FINANTELOR",
      "market": "REGT",
      "trades": 1,
      "volume": 10.0,
      "value": 1038.4,
      "open": 100.5311,
      "low": 100.5311,
      "high": 100.5311,
      "avg": 100.5311,
      "close": 100.5311,
      "refPrice": 102.199,
      "changePercent": -1.63
    },
    {
      "symbol": "R2910A",
      "name": "MINISTERUL FINANTELOR",
      "market": "REGT",
      "trades": 31,
      "volume": 9189.0,
      "value": 940179.28,
      "open": 99.7,
      "low": 99.61,
      "high": 99.89,
      "avg": 99.8254,
      "close": 99.88,
      "refPrice": 99.695,
      "changePercent": 0.19
    },
    {
      "symbol": "R2910AE",
      "name": "MINISTERUL FINANTELOR",
      "market": "EREGT",
      "trades": 5,
      "volume": 168.0,
      "value": 87225.75,
      "open": 99.72,
      "low": 99.72,
      "high": 100.15,
      "avg": 100.1423,
      "close": 100.15,
      "refPrice": 99.9,
      "changePercent": 0.25
    },
    {
      "symbol": "R2910C",
      "name": "MINISTERUL FINANTELOR",
      "market": "REGT",
      "trades": 6,
      "volume": 336.0,
      "value": 34963.6,
      "open": 100.302,
      "low": 100.302,
      "high": 101.5198,
      "avg": 101.4783,
      "close": 101.5198,
      "refPrice": 101.5,
      "changePercent": 0.02
    },
    {
      "symbol": "R2911A",
      "name": "MINISTERUL FINANTELOR",
      "market": "REGT",
      "trades": 1,
      "volume": 10.0,
      "value": 1024.4,
      "open": 100.505,
      "low": 100.505,
      "high": 100.505,
      "avg": 100.505,
      "close": 100.505,
      "refPrice": 102.7,
      "changePercent": -2.14
    },
    {
      "symbol": "R2912A",
      "name": "MINISTERUL FINANTELOR",
      "market": "REGT",
      "trades": 23,
      "volume": 1959.0,
      "value": 201141.98,
      "open": 101.3,
      "low": 101.2,
      "high": 101.74,
      "avg": 101.3856,
      "close": 101.74,
      "refPrice": 101.3,
      "changePercent": 0.43
    },
    {
      "symbol": "R2912C",
      "name": "MINISTERUL FINANTELOR",
      "market": "REGT",
      "trades": 3,
      "volume": 19.0,
      "value": 1911.08,
      "open": 98.6002,
      "low": 98.6002,
      "high": 100.0,
      "avg": 99.2633,
      "close": 100.0,
      "refPrice": 100.0,
      "changePercent": 0.0
    },
    {
      "symbol": "R3001A",
      "name": "MINISTERUL FINANTELOR",
      "market": "REGT",
      "trades": 1,
      "volume": 10.0,
      "value": 1005.1,
      "open": 100.0,
      "low": 100.0,
      "high": 100.0,
      "avg": 100.0,
      "close": 100.0,
      "refPrice": 98.7051,
      "changePercent": 1.31
    },
    {
      "symbol": "R3002A",
      "name": "MINISTERUL FINANTELOR",
      "market": "REGT",
      "trades": 82,
      "volume": 6447.0,
      "value": 664571.05,
      "open": 102.5001,
      "low": 102.32,
      "high": 103.25,
      "avg": 102.9922,
      "close": 102.9,
      "refPrice": 102.9,
      "changePercent": 0.0
    },
    {
      "symbol": "R3002C",
      "name": "MINISTERUL FINANTELOR",
      "market": "REGT",
      "trades": 3,
      "volume": 102.0,
      "value": 10234.68,
      "open": 100.25,
      "low": 100.25,
      "high": 100.25,
      "avg": 100.25,
      "close": 100.25,
      "refPrice": 100.0,
      "changePercent": 0.25
    },
    {
      "symbol": "R3003A",
      "name": "MINISTERUL FINANTELOR",
      "market": "REGT",
      "trades": 6,
      "volume": 83.0,
      "value": 9124.31,
      "open": 101.78,
      "low": 101.78,
      "high": 102.885,
      "avg": 102.6411,
      "close": 102.879,
      "refPrice": 101.8,
      "changePercent": 1.06
    },
    {
      "symbol": "R3004A",
      "name": "MINISTERUL FINANTELOR",
      "market": "REGT",
      "trades": 8,
      "volume": 148.0,
      "value": 15997.32,
      "open": 101.0,
      "low": 101.0,
      "high": 101.9,
      "avg": 101.57,
      "close": 101.9,
      "refPrice": 101.44,
      "changePercent": 0.45
    },
    {
      "symbol": "R3005A",
      "name": "MINISTERUL FINANTELOR",
      "market": "REGT",
      "trades": 1,
      "volume": 10.0,
      "value": 1077.9,
      "open": 101.85,
      "low": 101.85,
      "high": 101.85,
      "avg": 101.85,
      "close": 101.85,
      "refPrice": 102.848,
      "changePercent": -0.97
    },
    {
      "symbol": "R3006AE",
      "name": "MINISTERUL FINANTELOR",
      "market": "EREGT",
      "trades": 1,
      "volume": 10.0,
      "value": 5398.2,
      "open": 102.15,
      "low": 102.15,
      "high": 102.15,
      "avg": 102.15,
      "close": 102.15,
      "refPrice": 102.0,
      "changePercent": 0.15
    },
    {
      "symbol": "R3008AE",
      "name": "MINISTERUL FINANTELOR",
      "market": "EREGT",
      "trades": 2,
      "volume": 232.0,
      "value": 122071.44,
      "open": 100.4999,
      "low": 100.4999,
      "high": 100.5,
      "avg": 100.5,
      "close": 100.5,
      "refPrice": 100.4999,
      "changePercent": 0.0
    },
    {
      "symbol": "R3009AE",
      "name": "MINISTERUL FINANTELOR",
      "market": "EREGT",
      "trades": 1,
      "volume": 75.0,
      "value": 39233.25,
      "open": 100.4,
      "low": 100.4,
      "high": 100.4,
      "avg": 100.4,
      "close": 100.4,
      "refPrice": 100.75,
      "changePercent": -0.35
    },
    {
      "symbol": "R3010AE",
      "name": "MINISTERUL FINANTELOR",
      "market": "EREGT",
      "trades": 16,
      "volume": 125.0,
      "value": 64819.9,
      "open": 100.0199,
      "low": 100.0099,
      "high": 100.0199,
      "avg": 100.0158,
      "close": 100.01,
      "refPrice": 100.01,
      "changePercent": 0.0
    },
    {
      "symbol": "R3106A",
      "name": "MINISTERUL FINANTELOR",
      "market": "REGT",
      "trades": 4,
      "volume": 65.0,
      "value": 7090.5,
      "open": 102.5651,
      "low": 102.5651,
      "high": 103.8989,
      "avg": 103.663,
      "close": 103.8989,
      "refPrice": 102.9499,
      "changePercent": 0.92
    },
    {
      "symbol": "R3107A",
      "name": "MINISTERUL FINANTELOR",
      "market": "REGT",
      "trades": 7,
      "volume": 2268.0,
      "value": 245206.12,
      "open": 103.1,
      "low": 103.1,
      "high": 104.0,
      "avg": 103.2756,
      "close": 104.0,
      "refPrice": 103.0,
      "changePercent": 0.97
    },
    {
      "symbol": "R3108A",
      "name": "MINISTERUL FINANTELOR",
      "market": "REGT",
      "trades": 11,
      "volume": 653.0,
      "value": 70023.4,
      "open": 102.8,
      "low": 102.202,
      "high": 103.3799,
      "avg": 103.0332,
      "close": 103.3799,
      "refPrice": 102.99,
      "changePercent": 0.38
    },
    {
      "symbol": "R3109A",
      "name": "MINISTERUL FINANTELOR",
      "market": "REGT",
      "trades": 12,
      "volume": 127.0,
      "value": 13556.18,
      "open": 102.9382,
      "low": 102.938,
      "high": 104.2997,
      "avg": 103.3009,
      "close": 104.2997,
      "refPrice": 102.9381,
      "changePercent": 1.32
    },
    {
      "symbol": "R3110A",
      "name": "MINISTERUL FINANTELOR",
      "market": "REGT",
      "trades": 2,
      "volume": 20.0,
      "value": 2109.6,
      "open": 102.3001,
      "low": 102.3001,
      "high": 103.3,
      "avg": 102.8001,
      "close": 103.3,
      "refPrice": 103.0,
      "changePercent": 0.29
    },
    {
      "symbol": "R3111A",
      "name": "MINISTERUL FINANTELOR",
      "market": "REGT",
      "trades": 4,
      "volume": 84.0,
      "value": 8777.3,
      "open": 102.0,
      "low": 102.0,
      "high": 102.788,
      "avg": 102.4683,
      "close": 102.788,
      "refPrice": 102.2999,
      "changePercent": 0.48
    },
    {
      "symbol": "R3112A",
      "name": "MINISTERUL FINANTELOR",
      "market": "REGT",
      "trades": 19,
      "volume": 2587.0,
      "value": 266005.97,
      "open": 101.1,
      "low": 101.1,
      "high": 101.51,
      "avg": 101.4239,
      "close": 101.51,
      "refPrice": 101.2999,
      "changePercent": 0.21
    },
    {
      "symbol": "R3112AE",
      "name": "MINISTERUL FINANTELOR",
      "market": "EREGT",
      "trades": 25,
      "volume": 425.0,
      "value": 218756.55,
      "open": 100.0,
      "low": 99.9,
      "high": 100.21,
      "avg": 100.063,
      "close": 100.0,
      "refPrice": 100.0,
      "changePercent": 0.0
    },
    {
      "symbol": "R3201A",
      "name": "MINISTERUL FINANTELOR",
      "market": "REGT",
      "trades": 46,
      "volume": 5567.0,
      "value": 569356.95,
      "open": 101.294,
      "low": 100.9901,
      "high": 101.84,
      "avg": 101.743,
      "close": 101.84,
      "refPrice": 101.29,
      "changePercent": 0.54
    },
    {
      "symbol": "R3202A",
      "name": "MINISTERUL FINANTELOR",
      "market": "REGT",
      "trades": 41,
      "volume": 2709.0,
      "value": 272880.51,
      "open": 100.1,
      "low": 100.1,
      "high": 100.9797,
      "avg": 100.6313,
      "close": 100.689,
      "refPrice": 100.0,
      "changePercent": 0.69
    },
    {
      "symbol": "R3202AE",
      "name": "MINISTERUL FINANTELOR",
      "market": "EREGT",
      "trades": 65,
      "volume": 1094.0,
      "value": 566999.18,
      "open": 101.8,
      "low": 101.38,
      "high": 101.82,
      "avg": 101.6714,
      "close": 101.82,
      "refPrice": 101.8,
      "changePercent": 0.02
    },
    {
      "symbol": "R3203AE",
      "name": "MINISTERUL FINANTELOR",
      "market": "EREGT",
      "trades": 11,
      "volume": 151.0,
      "value": 81487.61,
      "open": 100.3,
      "low": 100.3,
      "high": 100.5,
      "avg": 100.3266,
      "close": 100.3,
      "refPrice": 100.598,
      "changePercent": -0.3
    },
    {
      "symbol": "R3204AE",
      "name": "MINISTERUL FINANTELOR",
      "market": "EREGT",
      "trades": 8,
      "volume": 121.0,
      "value": 65113.84,
      "open": 100.6,
      "low": 100.2101,
      "high": 100.6,
      "avg": 100.4884,
      "close": 100.5,
      "refPrice": 100.66,
      "changePercent": -0.16
    },
    {
      "symbol": "R3205AE",
      "name": "MINISTERUL FINANTELOR",
      "market": "EREGT",
      "trades": 1,
      "volume": 35.0,
      "value": 18997.3,
      "open": 101.79,
      "low": 101.79,
      "high": 101.79,
      "avg": 101.79,
      "close": 101.79,
      "refPrice": 101.799,
      "changePercent": -0.01
    },
    {
      "symbol": "R3206AE",
      "name": "MINISTERUL FINANTELOR",
      "market": "EREGT",
      "trades": 23,
      "volume": 374.0,
      "value": 204908.3,
      "open": 102.901,
      "low": 102.9,
      "high": 103.31,
      "avg": 103.1218,
      "close": 103.31,
      "refPrice": 103.25,
      "changePercent": 0.06
    },
    {
      "symbol": "R3207AE",
      "name": "MINISTERUL FINANTELOR",
      "market": "EREGT",
      "trades": 22,
      "volume": 341.0,
      "value": 183696.05,
      "open": 101.92,
      "low": 101.91,
      "high": 101.94,
      "avg": 101.9196,
      "close": 101.93,
      "refPrice": 101.92,
      "changePercent": 0.01
    },
    {
      "symbol": "R3508AE",
      "name": "MINISTERUL FINANTELOR",
      "market": "EREGT",
      "trades": 33,
      "volume": 484.0,
      "value": 263756.38,
      "open": 103.2995,
      "low": 103.29,
      "high": 103.8,
      "avg": 103.5262,
      "close": 103.7999,
      "refPrice": 103.29,
      "changePercent": 0.49
    },
    {
      "symbol": "R3509AE",
      "name": "MINISTERUL FINANTELOR",
      "market": "EREGT",
      "trades": 23,
      "volume": 307.0,
      "value": 166339.06,
      "open": 103.6998,
      "low": 103.0142,
      "high": 103.9999,
      "avg": 103.531,
      "close": 103.0142,
      "refPrice": 103.55,
      "changePercent": -0.52
    },
    {
      "symbol": "R3510AE",
      "name": "MINISTERUL FINANTELOR",
      "market": "EREGT",
      "trades": 2,
      "volume": 2.0,
      "value": 1081.88,
      "open": 103.9797,
      "low": 103.9797,
      "high": 103.9798,
      "avg": 103.9798,
      "close": 103.9798,
      "refPrice": 103.9449,
      "changePercent": 0.03
    },
    {
      "symbol": "R3511AE",
      "name": "MINISTERUL FINANTELOR",
      "market": "EREGT",
      "trades": 4,
      "volume": 24.0,
      "value": 12694.08,
      "open": 102.174,
      "low": 102.1687,
      "high": 102.174,
      "avg": 102.1694,
      "close": 102.1688,
      "refPrice": 102.174,
      "changePercent": -0.01
    },
    {
      "symbol": "R3512AE",
      "name": "MINISTERUL FINANTELOR",
      "market": "EREGT",
      "trades": 11,
      "volume": 36.0,
      "value": 18794.08,
      "open": 101.2998,
      "low": 101.2998,
      "high": 101.3399,
      "avg": 101.3287,
      "close": 101.3398,
      "refPrice": 101.2999,
      "changePercent": 0.04
    },
    {
      "symbol": "R3601AE",
      "name": "MINISTERUL FINANTELOR",
      "market": "EREGT",
      "trades": 31,
      "volume": 281.0,
      "value": 145646.07,
      "open": 101.3598,
      "low": 101.22,
      "high": 101.3886,
      "avg": 101.3076,
      "close": 101.38,
      "refPrice": 101.21,
      "changePercent": 0.17
    },
    {
      "symbol": "R3602AE",
      "name": "MINISTERUL FINANTELOR",
      "market": "EREGT",
      "trades": 28,
      "volume": 416.0,
      "value": 212999.66,
      "open": 100.4,
      "low": 100.35,
      "high": 100.5,
      "avg": 100.4317,
      "close": 100.4999,
      "refPrice": 100.0,
      "changePercent": 0.5
    },
    {
      "symbol": "MKR27E",
      "name": "MK KREDIT IFN S.A.",
      "market": "EXRB",
      "trades": 1,
      "volume": 7.0,
      "value": 3765.05,
      "open": 103.81,
      "low": 103.81,
      "high": 103.81,
      "avg": 103.81,
      "close": 103.81,
      "refPrice": 105.19,
      "changePercent": -1.31
    },
    {
      "symbol": "ASC27",
      "name": "OB. ASCENDIA - 2027",
      "market": "XRB",
      "trades": 4,
      "volume": 122.0,
      "value": 12146.06,
      "open": 99.38,
      "low": 99.38,
      "high": 99.79,
      "avg": 99.75,
      "close": 99.79,
      "refPrice": 99.36,
      "changePercent": 0.43
    },
    {
      "symbol": "OCIFN26E",
      "name": "OCEAN CREDIT IFN",
      "market": "EXRB",
      "trades": 1,
      "volume": 1.0,
      "value": 494.33,
      "open": 96.3,
      "low": 96.3,
      "high": 96.3,
      "avg": 96.3,
      "close": 96.3,
      "refPrice": 97.0,
      "changePercent": -0.72
    },
    {
      "symbol": "PBK27E",
      "name": "Patria Bank Obligatiuni 2027",
      "market": "EORDB",
      "trades": 1,
      "volume": 2.0,
      "value": 5201.28,
      "open": 99.29,
      "low": 99.29,
      "high": 99.29,
      "avg": 99.29,
      "close": 99.29,
      "refPrice": 99.0,
      "changePercent": 0.29
    },
    {
      "symbol": "PBK28E",
      "name": "Patria Bank Obligatiuni 2028 EUR",
      "market": "EORDB",
      "trades": 8,
      "volume": 50.0,
      "value": 129291.06,
      "open": 98.98,
      "low": 98.98,
      "high": 99.0,
      "avg": 98.99,
      "close": 99.0,
      "refPrice": 98.98,
      "changePercent": 0.02
    },
    {
      "symbol": "SKI29",
      "name": "SKI SURIANU - 2029",
      "market": "XRB",
      "trades": 5,
      "volume": 445.0,
      "value": 43498.44,
      "open": 95.5,
      "low": 94.51,
      "high": 95.5,
      "avg": 95.42,
      "close": 94.51,
      "refPrice": 96.9,
      "changePercent": -2.47
    },
    {
      "symbol": "BRK26",
      "name": "SSIF BRK FINANCIAL GROUP - Ob. 2026",
      "market": "ORDB",
      "trades": 14,
      "volume": 525.0,
      "value": 51890.82,
      "open": 98.59,
      "low": 98.59,
      "high": 98.85,
      "avg": 98.78,
      "close": 98.8,
      "refPrice": 97.99,
      "changePercent": 0.83
    },
    {
      "symbol": "SBET29",
      "name": "Stanleybet Capital",
      "market": "XRB",
      "trades": 5,
      "volume": 598.0,
      "value": 58470.61,
      "open": 97.5,
      "low": 97.15,
      "high": 97.5,
      "avg": 97.48,
      "close": 97.16,
      "refPrice": 97.5,
      "changePercent": -0.35
    },
    {
      "symbol": "TEI26",
      "name": "Teilor Holding S.A. - obligatiuni 2026",
      "market": "XRB",
      "trades": 3,
      "volume": 500.0,
      "value": 50521.52,
      "open": 99.1,
      "low": 99.1,
      "high": 99.2,
      "avg": 99.19,
      "close": 99.2,
      "refPrice": 99.1,
      "changePercent": 0.1
    },
    {
      "symbol": "TEI26E",
      "name": "Teilor Holding S.A. - obligatiuni 26E",
      "market": "EXRB",
      "trades": 2,
      "volume": 8.0,
      "value": 4086.8,
      "open": 98.99,
      "low": 98.99,
      "high": 98.99,
      "avg": 98.99,
      "close": 98.99,
      "refPrice": 98.55,
      "changePercent": 0.45
    }
  ]
}